georasters/__init__.py
georasters/georasters.py
georasters-0.5.28.dist-info/LICENSE.txt
georasters-0.5.28.dist-info/METADATA
georasters-0.5.28.dist-info/WHEEL
georasters-0.5.28.dist-info/pbr.json
georasters-0.5.28.dist-info/top_level.txt
georasters-0.5.28.dist-info/RECORD
