Metadata-Version: 2.1
Name: georasters
Version: 0.5.28
Summary: Tools for working with Geographical Information System Rasters
Home-page: http://github.com/ozak/georasters
Author: Ömer Özak
Author-email: omer@omerozak.com
License: GPLv3
Keywords: gis geospatial geographic raster vector zonal statistics spatial analysis
Classifier: Development Status :: 3 - Alpha
Classifier: Topic :: Utilities
Classifier: License :: OSI Approved :: GNU General Public License v3 or later (GPLv3+)
Classifier: Intended Audience :: Developers
Classifier: Intended Audience :: Science/Research
Classifier: Operating System :: OS Independent
Classifier: Programming Language :: Python
Classifier: Topic :: Scientific/Engineering :: GIS
Classifier: Programming Language :: Python :: 2
Classifier: Programming Language :: Python :: 2.7
Classifier: Programming Language :: Python :: 3
Classifier: Programming Language :: Python :: 3.4
Classifier: Programming Language :: Python :: 3.5
Classifier: Programming Language :: Python :: 3.6
Classifier: Programming Language :: Python :: 3.7
Classifier: Programming Language :: Python :: 3.8
Classifier: Programming Language :: Python :: 3.9
Classifier: Programming Language :: Python :: 3.10
License-File: LICENSE.txt
Requires-Dist: numpy
Requires-Dist: pandas
Requires-Dist: docopt
Requires-Dist: GDAL
Requires-Dist: pyproj
Requires-Dist: scikit-image
Requires-Dist: matplotlib
Requires-Dist: coverage
Requires-Dist: fiona
Requires-Dist: geopandas
Requires-Dist: pysal
Requires-Dist: affine
Requires-Dist: rasterstats
